TPLSp/TPLScode.py
TPLSp/__init__.py
TPLSp-1.1.0.dist-info/LICENSE
TPLSp-1.1.0.dist-info/METADATA
TPLSp-1.1.0.dist-info/WHEEL
TPLSp-1.1.0.dist-info/top_level.txt
TPLSp-1.1.0.dist-info/RECORD
