Metadata-Version: 2.1
Name: TPLSp
Version: 1.1.0
Summary: Python package for thresholded partial least squares
Home-page: https://github.com/sangillee/TPLSp
Author: Arthur Lee
Author-email: sangillee3rd@gmail.com
Project-URL: Publication, https://doi.org/10.1016/j.crmeth.2022.100227
Classifier: Programming Language :: Python :: 3
Classifier: License :: OSI Approved :: MIT License
Classifier: Operating System :: OS Independent
Requires-Python: >=3.6
License-File: LICENSE
